odoo/addons/project_task_subtask_inline/README.rst
odoo/addons/project_task_subtask_inline/__init__.py
odoo/addons/project_task_subtask_inline/__manifest__.py
odoo/addons/project_task_subtask_inline/readme/CONFIGURE.rst
odoo/addons/project_task_subtask_inline/readme/CONTRIBUTORS.rst
odoo/addons/project_task_subtask_inline/readme/DESCRIPTION.rst
odoo/addons/project_task_subtask_inline/readme/USAGE.rst
odoo/addons/project_task_subtask_inline/static/description/icon.png
odoo/addons/project_task_subtask_inline/static/description/index.html
odoo/addons/project_task_subtask_inline/views/project_task_views.xml
odoo_addon_project_task_subtask_inline-16.0.1.0.0.1.dist-info/METADATA
odoo_addon_project_task_subtask_inline-16.0.1.0.0.1.dist-info/WHEEL
odoo_addon_project_task_subtask_inline-16.0.1.0.0.1.dist-info/top_level.txt
odoo_addon_project_task_subtask_inline-16.0.1.0.0.1.dist-info/RECORD
